{ "TripList": {"CurrentTime": 1470268015,"Line": "Red", "Trips": [{"TripID": "31286089", "Destination": "Alewife", "Position": {"Timestamp": 1470267905, "Train": "94BC", "Lat": 42.39676, "Long": -71.12241,"Heading": 285}, "Predictions": [
{"StopID": "70061", "Stop": "Alewife", "Seconds": 149}]},
{"TripID": "31285866", "Destination": "Ashmont", "Position": {"Timestamp": 1470267974, "Train": "94C1", "Lat": 42.37285, "Long": -71.11679,"Heading": 130}, "Predictions": [
{"StopID": "70069", "Stop": "Central Square", "Seconds": 108},
{"StopID": "70071", "Stop": "Kendall/MIT", "Seconds": 265},
{"StopID": "70073", "Stop": "Charles/MGH", "Seconds": 409},
{"StopID": "70075", "Stop": "Park Street", "Seconds": 561},
{"StopID": "70077", "Stop": "Downtown Crossing", "Seconds": 668},
{"StopID": "70079", "Stop": "South Station", "Seconds": 765},
{"StopID": "70081", "Stop": "Broadway", "Seconds": 910},
{"StopID": "70083", "Stop": "Andrew", "Seconds": 1042},
{"StopID": "70085", "Stop": "JFK/UMass", "Seconds": 1191}]},
{"TripID": "31285960", "Destination": "Braintree", "Position": {"Timestamp": 1470267971, "Train": "91D7", "Lat": 42.23131, "Long": -71.00711,"Heading": 180}, "Predictions": [
{"StopID": "70105", "Stop": "Braintree", "Seconds": 224}]},
{"TripID": "31286111", "Destination": "Ashmont", "Position": {"Timestamp": 1470267571, "Train": "979B", "Lat": 42.39621, "Long": -71.14054,"Heading": 265}, "Predictions": [
{"StopID": "70063", "Stop": "Davis", "Seconds": 68},
{"StopID": "70065", "Stop": "Porter Square", "Seconds": 191},
{"StopID": "70067", "Stop": "Harvard Square", "Seconds": 367},
{"StopID": "70069", "Stop": "Central Square", "Seconds": 578},
{"StopID": "70071", "Stop": "Kendall/MIT", "Seconds": 738}]},
{"TripID": "31285876", "Destination": "Ashmont", "Position": {"Timestamp": 1470267958, "Train": "94BE", "Lat": 42.30377, "Long": -71.05578,"Heading": 195}, "Predictions": [
{"StopID": "70089", "Stop": "Fields Corner", "Seconds": 3},
{"StopID": "70091", "Stop": "Shawmut", "Seconds": 145},
{"StopID": "70093", "Stop": "Ashmont", "Seconds": 301}]},
{"TripID": "31285963", "Destination": "Braintree", "Position": {"Timestamp": 1470267958, "Train": "94C4", "Lat": 42.35524, "Long": -71.06018,"Heading": 135}, "Predictions": [
{"StopID": "70079", "Stop": "South Station", "Seconds": 39},
{"StopID": "70081", "Stop": "Broadway", "Seconds": 184},
{"StopID": "70083", "Stop": "Andrew", "Seconds": 316},
{"StopID": "70095", "Stop": "JFK/UMass", "Seconds": 464},
{"StopID": "70097", "Stop": "North Quincy", "Seconds": 969},
{"StopID": "70099", "Stop": "Wollaston", "Seconds": 1094}]},
{"TripID": "31286097", "Destination": "Alewife", "Predictions": [
{"StopID": "70094", "Stop": "Ashmont", "Seconds": 724},
{"StopID": "70092", "Stop": "Shawmut", "Seconds": 798},
{"StopID": "70090", "Stop": "Fields Corner", "Seconds": 910},
{"StopID": "70088", "Stop": "Savin Hill", "Seconds": 1087}]},
{"TripID": "31285864", "Destination": "Ashmont", "Position": {"Timestamp": 1470267909, "Train": "8ED6", "Lat": 42.36122, "Long": -71.07162,"Heading": 95}, "Predictions": [
{"StopID": "70075", "Stop": "Park Street", "Seconds": 45},
{"StopID": "70077", "Stop": "Downtown Crossing", "Seconds": 144},
{"StopID": "70079", "Stop": "South Station", "Seconds": 241},
{"StopID": "70081", "Stop": "Broadway", "Seconds": 390},
{"StopID": "70083", "Stop": "Andrew", "Seconds": 522},
{"StopID": "70085", "Stop": "JFK/UMass", "Seconds": 671},
{"StopID": "70087", "Stop": "Savin Hill", "Seconds": 814},
{"StopID": "70089", "Stop": "Fields Corner", "Seconds": 1014},
{"StopID": "70091", "Stop": "Shawmut", "Seconds": 1156}]},
{"TripID": "31286168", "Destination": "Alewife", "Position": {"Timestamp": 1470267595, "Train": "914E", "Lat": 42.20749, "Long": -71.00173,"Heading": 190}, "Predictions": [
{"StopID": "70105", "Stop": "Braintree", "Seconds": 304},
{"StopID": "70104", "Stop": "Quincy Adams", "Seconds": 548},
{"StopID": "70102", "Stop": "Quincy Center", "Seconds": 746},
{"StopID": "70100", "Stop": "Wollaston", "Seconds": 931},
{"StopID": "70098", "Stop": "North Quincy", "Seconds": 1067}]},
{"TripID": "31286108", "Destination": "Alewife", "Position": {"Timestamp": 1470267944, "Train": "94BF", "Lat": 42.32589, "Long": -71.05635,"Heading": 305}, "Predictions": [
{"StopID": "70084", "Stop": "Andrew", "Seconds": -29},
{"StopID": "70082", "Stop": "Broadway", "Seconds": 105},
{"StopID": "70080", "Stop": "South Station", "Seconds": 255},
{"StopID": "70078", "Stop": "Downtown Crossing", "Seconds": 342},
{"StopID": "70076", "Stop": "Park Street", "Seconds": 442},
{"StopID": "70074", "Stop": "Charles/MGH", "Seconds": 588},
{"StopID": "70072", "Stop": "Kendall/MIT", "Seconds": 741},
{"StopID": "70070", "Stop": "Central Square", "Seconds": 894},
{"StopID": "70068", "Stop": "Harvard Square", "Seconds": 1095}]},
{"TripID": "31285962", "Destination": "Braintree", "Position": {"Timestamp": 1470267954, "Train": "97C7", "Lat": 42.31602, "Long": -71.05206,"Heading": 170}, "Predictions": [
{"StopID": "70097", "Stop": "North Quincy", "Seconds": 358},
{"StopID": "70099", "Stop": "Wollaston", "Seconds": 483},
{"StopID": "70101", "Stop": "Quincy Center", "Seconds": 656},
{"StopID": "70103", "Stop": "Quincy Adams", "Seconds": 852},
{"StopID": "70105", "Stop": "Braintree", "Seconds": 1134}]},
{"TripID": "31286109", "Destination": "Ashmont", "Predictions": [
{"StopID": "70061", "Stop": "Alewife", "Seconds": 1180}]},
{"TripID": "31286110", "Destination": "Ashmont", "Predictions": [
{"StopID": "70061", "Stop": "Alewife", "Seconds": 424},
{"StopID": "70063", "Stop": "Davis", "Seconds": 521},
{"StopID": "70065", "Stop": "Porter Square", "Seconds": 644},
{"StopID": "70067", "Stop": "Harvard Square", "Seconds": 816},
{"StopID": "70069", "Stop": "Central Square", "Seconds": 1027},
{"StopID": "70071", "Stop": "Kendall/MIT", "Seconds": 1184}]},
{"TripID": "31286145", "Destination": "Braintree", "Predictions": [
{"StopID": "70061", "Stop": "Alewife", "Seconds": 1080},
{"StopID": "70063", "Stop": "Davis", "Seconds": 1177}]},
{"TripID": "31286140", "Destination": "Alewife", "Position": {"Timestamp": 1470267910, "Train": "716A", "Lat": 42.39638, "Long": -71.1386,"Heading": 260}, "Predictions": [
{"StopID": "70061", "Stop": "Alewife", "Seconds": -7}]},
{"TripID": "31286088", "Destination": "Alewife", "Position": {"Timestamp": 1470267981, "Train": "97D6", "Lat": 42.36203, "Long": -71.08088,"Heading": 275}, "Predictions": [
{"StopID": "70072", "Stop": "Kendall/MIT", "Seconds": 13},
{"StopID": "70070", "Stop": "Central Square", "Seconds": 166},
{"StopID": "70068", "Stop": "Harvard Square", "Seconds": 367},
{"StopID": "70066", "Stop": "Porter Square", "Seconds": 559},
{"StopID": "70064", "Stop": "Davis", "Seconds": 681},
{"StopID": "70061", "Stop": "Alewife", "Seconds": 941}]},
{"TripID": "31286139", "Destination": "Braintree", "Position": {"Timestamp": 1470267950, "Train": "716A", "Lat": 42.39618, "Long": -71.14054,"Heading": 265}, "Predictions": [
{"StopID": "70061", "Stop": "Alewife", "Seconds": 244},
{"StopID": "70063", "Stop": "Davis", "Seconds": 341},
{"StopID": "70065", "Stop": "Porter Square", "Seconds": 463},
{"StopID": "70067", "Stop": "Harvard Square", "Seconds": 635},
{"StopID": "70069", "Stop": "Central Square", "Seconds": 846},
{"StopID": "70071", "Stop": "Kendall/MIT", "Seconds": 1003}]},
{"TripID": "31286156", "Destination": "Alewife", "Position": {"Timestamp": 1470267906, "Train": "992C", "Lat": 42.28579, "Long": -71.03854,"Heading": 330}, "Predictions": [
{"StopID": "70096", "Stop": "JFK/UMass", "Seconds": 220},
{"StopID": "70084", "Stop": "Andrew", "Seconds": 380},
{"StopID": "70082", "Stop": "Broadway", "Seconds": 515},
{"StopID": "70080", "Stop": "South Station", "Seconds": 665},
{"StopID": "70078", "Stop": "Downtown Crossing", "Seconds": 752},
{"StopID": "70076", "Stop": "Park Street", "Seconds": 852},
{"StopID": "70074", "Stop": "Charles/MGH", "Seconds": 998},
{"StopID": "70072", "Stop": "Kendall/MIT", "Seconds": 1151}]},
{"TripID": "31286152", "Destination": "Alewife", "Position": {"Timestamp": 1470267963, "Train": "9530", "Lat": 42.3565, "Long": -71.06263,"Heading": 310}, "Predictions": [
{"StopID": "70074", "Stop": "Charles/MGH", "Seconds": 93},
{"StopID": "70072", "Stop": "Kendall/MIT", "Seconds": 246},
{"StopID": "70070", "Stop": "Central Square", "Seconds": 399},
{"StopID": "70068", "Stop": "Harvard Square", "Seconds": 600},
{"StopID": "70066", "Stop": "Porter Square", "Seconds": 792},
{"StopID": "70064", "Stop": "Davis", "Seconds": 914},
{"StopID": "70061", "Stop": "Alewife", "Seconds": 1174}]},
{"TripID": "31286173", "Destination": "Alewife", "Predictions": [
{"StopID": "70105", "Stop": "Braintree", "Seconds": 1002}]},
{"TripID": "31285961", "Destination": "Braintree", "Position": {"Timestamp": 1470267972, "Train": "9578", "Lat": 42.28577, "Long": -71.03887,"Heading": 135}, "Predictions": [
{"StopID": "70097", "Stop": "North Quincy", "Seconds": 58},
{"StopID": "70099", "Stop": "Wollaston", "Seconds": 183},
{"StopID": "70101", "Stop": "Quincy Center", "Seconds": 356},
{"StopID": "70103", "Stop": "Quincy Adams", "Seconds": 552},
{"StopID": "70105", "Stop": "Braintree", "Seconds": 834}]},
{"TripID": "31285862", "Destination": "Ashmont", "Position": {"Timestamp": 1470267978, "Train": "982B", "Lat": 42.34759, "Long": -71.05417,"Heading": 210}, "Predictions": [
{"StopID": "70081", "Stop": "Broadway", "Seconds": -5},
{"StopID": "70083", "Stop": "Andrew", "Seconds": 126},
{"StopID": "70085", "Stop": "JFK/UMass", "Seconds": 275},
{"StopID": "70087", "Stop": "Savin Hill", "Seconds": 418},
{"StopID": "70089", "Stop": "Fields Corner", "Seconds": 618},
{"StopID": "70091", "Stop": "Shawmut", "Seconds": 760},
{"StopID": "70093", "Stop": "Ashmont", "Seconds": 916}]},
{"TripID": "31286162", "Destination": "Alewife", "Position": {"Timestamp": 1470267983, "Train": "819C", "Lat": 42.24018, "Long": -71.00518,"Heading": 15}, "Predictions": [
{"StopID": "70102", "Stop": "Quincy Center", "Seconds": 97},
{"StopID": "70100", "Stop": "Wollaston", "Seconds": 288},
{"StopID": "70098", "Stop": "North Quincy", "Seconds": 422},
{"StopID": "70096", "Stop": "JFK/UMass", "Seconds": 869},
{"StopID": "70084", "Stop": "Andrew", "Seconds": 1029},
{"StopID": "70082", "Stop": "Broadway", "Seconds": 1164}]},
{"TripID": "31286146", "Destination": "Alewife", "Position": {"Timestamp": 1470267984, "Train": "94C6", "Lat": 42.36267, "Long": -71.08724,"Heading": 275}, "Predictions": [
{"StopID": "70070", "Stop": "Central Square", "Seconds": 66},
{"StopID": "70068", "Stop": "Harvard Square", "Seconds": 259},
{"StopID": "70066", "Stop": "Porter Square", "Seconds": 459},
{"StopID": "70064", "Stop": "Davis", "Seconds": 581},
{"StopID": "70061", "Stop": "Alewife", "Seconds": 841}]},
{"TripID": "31286115", "Destination": "Alewife", "Position": {"Timestamp": 1470267761, "Train": "97EB", "Lat": 42.28458, "Long": -71.06377,"Heading": 330}, "Predictions": [
{"StopID": "70094", "Stop": "Ashmont", "Seconds": 4},
{"StopID": "70092", "Stop": "Shawmut", "Seconds": 78},
{"StopID": "70090", "Stop": "Fields Corner", "Seconds": 190},
{"StopID": "70088", "Stop": "Savin Hill", "Seconds": 367},
{"StopID": "70086", "Stop": "JFK/UMass", "Seconds": 497}]},
{"TripID": "31286132", "Destination": "Braintree", "Position": {"Timestamp": 1470267956, "Train": "81EA", "Lat": 42.38826, "Long": -71.11895,"Heading": 180}, "Predictions": [
{"StopID": "70067", "Stop": "Harvard Square", "Seconds": 112},
{"StopID": "70069", "Stop": "Central Square", "Seconds": 323},
{"StopID": "70071", "Stop": "Kendall/MIT", "Seconds": 480},
{"StopID": "70073", "Stop": "Charles/MGH", "Seconds": 624},
{"StopID": "70075", "Stop": "Park Street", "Seconds": 776},
{"StopID": "70077", "Stop": "Downtown Crossing", "Seconds": 883},
{"StopID": "70079", "Stop": "South Station", "Seconds": 980},
{"StopID": "70081", "Stop": "Broadway", "Seconds": 1125}]},
{"TripID": "31285964", "Destination": "Braintree", "Position": {"Timestamp": 1470267975, "Train": "9196", "Lat": 42.36228, "Long": -71.08379,"Heading": 95}, "Predictions": [
{"StopID": "70073", "Stop": "Charles/MGH", "Seconds": 52},
{"StopID": "70075", "Stop": "Park Street", "Seconds": 204},
{"StopID": "70077", "Stop": "Downtown Crossing", "Seconds": 311},
{"StopID": "70079", "Stop": "South Station", "Seconds": 408},
{"StopID": "70081", "Stop": "Broadway", "Seconds": 553},
{"StopID": "70083", "Stop": "Andrew", "Seconds": 685},
{"StopID": "70095", "Stop": "JFK/UMass", "Seconds": 833}]}]}}